okdata_sdk-3.4.0-py3.13-nspkg.pth
okdata/sdk/__init__.py
okdata/sdk/config.py
okdata/sdk/exceptions.py
okdata/sdk/file_cache.py
okdata/sdk/io_utils.py
okdata/sdk/py.typed
okdata/sdk/sdk.py
okdata/sdk/auth/__init__.py
okdata/sdk/auth/auth.py
okdata/sdk/auth/credentials/__init__.py
okdata/sdk/auth/credentials/client_credentials.py
okdata/sdk/auth/credentials/common.py
okdata/sdk/auth/credentials/password_grant.py
okdata/sdk/data/__init__.py
okdata/sdk/data/dataset.py
okdata/sdk/data/download.py
okdata/sdk/data/upload.py
okdata/sdk/permission/client.py
okdata/sdk/permission/user_types.py
okdata/sdk/pipelines/__init__.py
okdata/sdk/pipelines/client.py
okdata/sdk/pipelines/resources/__init__.py
okdata/sdk/pipelines/resources/pipeline.py
okdata/sdk/pipelines/resources/pipeline_base.py
okdata/sdk/pipelines/resources/pipeline_input.py
okdata/sdk/pipelines/resources/pipeline_instance.py
okdata/sdk/pipelines/resources/schema.py
okdata/sdk/pipelines/resources/schemas/pipeline-inputs.json
okdata/sdk/pipelines/resources/schemas/pipeline-instances.json
okdata/sdk/pipelines/resources/schemas/pipelines.json
okdata/sdk/pipelines/resources/schemas/schemas.json
okdata/sdk/status/__init__.py
okdata/sdk/status/status.py
okdata/sdk/team/client.py
okdata_sdk-3.4.0.data/data/schema/pipeline-inputs.json
okdata_sdk-3.4.0.data/data/schema/pipeline-instances.json
okdata_sdk-3.4.0.data/data/schema/pipelines.json
okdata_sdk-3.4.0.data/data/schema/schemas.json
okdata_sdk-3.4.0.dist-info/licenses/LICENSE
okdata_sdk-3.4.0.dist-info/METADATA
okdata_sdk-3.4.0.dist-info/WHEEL
okdata_sdk-3.4.0.dist-info/namespace_packages.txt
okdata_sdk-3.4.0.dist-info/top_level.txt
okdata_sdk-3.4.0.dist-info/RECORD
