Metadata-Version: 2.4
Name: okdata-sdk
Version: 3.4.0
Summary: SDK for origo dataplatform
Home-page: https://github.com/oslokommune/okdata-sdk-python
Author: Oslo Origo
Author-email: dataplattform@oslo.kommune.no
Classifier: Development Status :: 5 - Production/Stable
Classifier: Programming Language :: Python :: 3.9
Classifier: Programming Language :: Python :: 3.10
Classifier: Programming Language :: Python :: 3.11
Classifier: Programming Language :: Python :: 3.12
Classifier: Programming Language :: Python :: 3.13
Classifier: License :: OSI Approved :: MIT License
Classifier: Operating System :: OS Independent
Requires-Python: >=3.9
License-File: LICENSE
Requires-Dist: jsonschema
Requires-Dist: python-keycloak<4,>=3.9.1
Requires-Dist: requests<3,>=2.25
Requires-Dist: urllib3<3,>=1.26
Dynamic: author
Dynamic: author-email
Dynamic: classifier
Dynamic: description
Dynamic: description-content-type
Dynamic: home-page
Dynamic: license-file
Dynamic: requires-dist
Dynamic: requires-python
Dynamic: summary
